{
	"info": {
		"_postman_id": "edf4bb29-1958-485e-838f-fa9388714c93",
		"name": "Softxpert",
		"schema": "https://schema.getpostman.com/json/collection/v2.1.0/collection.json",
		"_exporter_id": "27167134"
	},
	"item": [
		{
			"name": "Auth",
			"item": [
				{
					"name": "UserLogin",
					"request": {
						"method": "POST",
						"header": [
							{
								"key": "Accept",
								"value": "application/json",
								"type": "text"
							}
						],
						"body": {
							"mode": "formdata",
							"formdata": [
								{
									"key": "email",
									"value": "user11@gmail.com",
									"type": "text"
								},
								{
									"key": "password",
									"value": "password",
									"type": "text"
								}
							]
						},
						"url": {
							"raw": "{{local}}/v1/login",
							"host": [
								"{{local}}"
							],
							"path": [
								"v1",
								"login"
							]
						}
					},
					"response": []
				},
				{
					"name": "ManagerLogin",
					"request": {
						"method": "POST",
						"header": [
							{
								"key": "Accept",
								"value": "application/json",
								"type": "text"
							}
						],
						"body": {
							"mode": "formdata",
							"formdata": [
								{
									"key": "email",
									"value": "manager11@gmail.com",
									"type": "text"
								},
								{
									"key": "password",
									"value": "password",
									"type": "text"
								}
							]
						},
						"url": {
							"raw": "{{local}}/v1/login",
							"host": [
								"{{local}}"
							],
							"path": [
								"v1",
								"login"
							]
						}
					},
					"response": []
				}
			]
		},
		{
			"name": "Task",
			"item": [
				{
					"name": "all",
					"protocolProfileBehavior": {
						"disableBodyPruning": true
					},
					"request": {
						"auth": {
							"type": "bearer",
							"bearer": [
								{
									"key": "token",
									"value": "{{token}}",
									"type": "string"
								}
							]
						},
						"method": "GET",
						"header": [
							{
								"key": "Accept",
								"value": "application/json",
								"type": "text"
							}
						],
						"body": {
							"mode": "formdata",
							"formdata": []
						},
						"url": {
							"raw": "{{local}}/v1/tasks",
							"host": [
								"{{local}}"
							],
							"path": [
								"v1",
								"tasks"
							]
						}
					},
					"response": []
				},
				{
					"name": "update",
					"protocolProfileBehavior": {
						"disableBodyPruning": true
					},
					"request": {
						"auth": {
							"type": "bearer",
							"bearer": [
								{
									"key": "token",
									"value": "{{token}}",
									"type": "string"
								}
							]
						},
						"method": "GET",
						"header": [
							{
								"key": "Accept",
								"value": "application/json",
								"type": "text"
							}
						],
						"body": {
							"mode": "formdata",
							"formdata": []
						},
						"url": {
							"raw": "{{local}}/v1/tasks",
							"host": [
								"{{local}}"
							],
							"path": [
								"v1",
								"tasks"
							]
						}
					},
					"response": []
				},
				{
					"name": "create",
					"request": {
						"auth": {
							"type": "bearer",
							"bearer": [
								{
									"key": "token",
									"value": "{{token}}",
									"type": "string"
								}
							]
						},
						"method": "POST",
						"header": [
							{
								"key": "Accept",
								"value": "application/json",
								"type": "text"
							}
						],
						"body": {
							"mode": "formdata",
							"formdata": [
								{
									"key": "title",
									"value": "New Task",
									"type": "text"
								},
								{
									"key": "description",
									"value": "Details",
									"type": "text"
								},
								{
									"key": "due_date",
									"value": "2025-08-30",
									"type": "text"
								},
								{
									"key": "assignee_id",
									"value": "1",
									"type": "text"
								}
							]
						},
						"url": {
							"raw": "{{local}}/v1/tasks",
							"host": [
								"{{local}}"
							],
							"path": [
								"v1",
								"tasks"
							]
						}
					},
					"response": []
				}
			]
		}
	]
}